steelflask/__init__.py
steelflask/cli.py
steelflask/ext.py
steelflask/version.py
steelflask/actions/__init__.py
steelflask/actions/app_actions.py
steelflask/templates/basicapp/.editorconfig
steelflask/templates/basicapp/.envactivate.mako
steelflask/templates/basicapp/.gitignore.mako
steelflask/templates/basicapp/MANIFEST.in.mako
steelflask/templates/basicapp/README.md.mako
steelflask/templates/basicapp/pyproject.toml
steelflask/templates/basicapp/requirements_dev.txt
steelflask/templates/basicapp/setup.cfg.mako
steelflask/templates/basicapp/setup.py.mako
steelflask/templates/basicapp/steelflaskapp/__init__.py.mako
steelflask/templates/basicapp/tests/__init__.py.mako
steelflask/templates/flaskapp/.editorconfig
steelflask/templates/flaskapp/.envactivate.mako
steelflask/templates/flaskapp/.gitignore.mako
steelflask/templates/flaskapp/MANIFEST.in.mako
steelflask/templates/flaskapp/README.md.mako
steelflask/templates/flaskapp/pyproject.toml
steelflask/templates/flaskapp/requirements_dev.txt
steelflask/templates/flaskapp/setup.cfg.mako
steelflask/templates/flaskapp/setup.py.mako
steelflask/templates/flaskapp/steelflaskapp/__init__.py.mako
steelflask/templates/flaskapp/steelflaskapp/app_factory.py.mako
steelflask/templates/flaskapp/steelflaskapp/configuration.py.mako
steelflask/templates/flaskapp/steelflaskapp/errorhandler.py.mako
steelflask/templates/flaskapp/steelflaskapp/exceptions.py.mako
steelflask/templates/flaskapp/steelflaskapp/ext.py.mako
steelflask/templates/flaskapp/tests/__init__.py.mako
steelflask/templates/flaskapp/tests/configuration.py.mako
steelflask/templates/flaskapp/tests/conftest.py.mako
steelflask/templates/flaskapp/tests/test_app_setup.py.mako
steelflask-0.1.0.dist-info/LICENSE
steelflask-0.1.0.dist-info/METADATA
steelflask-0.1.0.dist-info/WHEEL
steelflask-0.1.0.dist-info/entry_points.txt
steelflask-0.1.0.dist-info/top_level.txt
steelflask-0.1.0.dist-info/RECORD
