Metadata-Version: 2.1
Name: steelflask
Version: 0.1.0
Summary: Opinionated flask app scaffolding tool.
Home-page: https://github.com/chandrakantap/steelflask.git
Author: Chandrakanta Pal
Author-email: pal.chandrakanta@gmail.com
License: UNKNOWN
Keywords: flask scaffolding
Platform: UNKNOWN
Requires-Dist: Click (>=7.0)
Requires-Dist: Mako (>=1.1.2)
